plone.indexer-2.0.2-py3.13-nspkg.pth
plone/indexer/README.rst
plone/indexer/__init__.py
plone/indexer/configure.zcml
plone/indexer/decorator.py
plone/indexer/delegate.py
plone/indexer/interfaces.py
plone/indexer/tests.py
plone/indexer/wrapper.py
plone_indexer-2.0.2.dist-info/METADATA
plone_indexer-2.0.2.dist-info/WHEEL
plone_indexer-2.0.2.dist-info/namespace_packages.txt
plone_indexer-2.0.2.dist-info/top_level.txt
plone_indexer-2.0.2.dist-info/RECORD
